red9/__init__.py
red9/__main__.py
red9/approval.py
red9/audit.py
red9/errors.py
red9/logging.py
red9/metrics.py
red9/py.typed
red9/server.py
red9/agents/__init__.py
red9/agents/compression.py
red9/agents/context_injector.py
red9/agents/error_handler.py
red9/agents/loop.py
red9/agents/loop_detector.py
red9/agents/notepad.py
red9/agents/personas.py
red9/agents/prompt_examples.py
red9/agents/prompts.py
red9/agents/swarm_prompts.py
red9/agents/tokens.py
red9/agents/hooks/__init__.py
red9/agents/hooks/todo_enforcer.py
red9/agents/personas/__init__.py
red9/agents/personas/architect.py
red9/agents/personas/explorer.py
red9/agents/personas/implementer.py
red9/agents/personas/reviewer.py
red9/agents/tasks/__init__.py
red9/agents/tasks/approval_gate.py
red9/agents/tasks/architect.py
red9/agents/tasks/code.py
red9/agents/tasks/compensation.py
red9/agents/tasks/context.py
red9/agents/tasks/ddd.py
red9/agents/tasks/ddd_retry.py
red9/agents/tasks/decompose.py
red9/agents/tasks/diagnosis.py
red9/agents/tasks/docs_sync.py
red9/agents/tasks/explorer.py
red9/agents/tasks/index_setup.py
red9/agents/tasks/issue_complete.py
red9/agents/tasks/issue_setup.py
red9/agents/tasks/iteration_loop.py
red9/agents/tasks/merge.py
red9/agents/tasks/plan.py
red9/agents/tasks/reviewer.py
red9/agents/tasks/simple_code.py
red9/agents/tasks/spec.py
red9/agents/tasks/swarm_agent.py
red9/agents/tasks/swarm_aggregator.py
red9/agents/tasks/test.py
red9/agents/tasks/test_run.py
red9/agents/tasks/test_write.py
red9/api/__init__.py
red9/api/main.py
red9/api/routes/__init__.py
red9/api/routes/health.py
red9/api/routes/items.py
red9/cli/__init__.py
red9/cli/error_handler.py
red9/cli/main.py
red9/cli/output.py
red9/cli/spinner.py
red9/cli/streaming.py
red9/cli/ui.py
red9/cli/commands/__init__.py
red9/cli/commands/ask.py
red9/cli/commands/chat.py
red9/cli/commands/init.py
red9/cli/commands/lessons.py
red9/cli/commands/memory.py
red9/cli/commands/resume.py
red9/cli/commands/status.py
red9/cli/commands/task.py
red9-0.1.0.dist-info/METADATA
red9-0.1.0.dist-info/WHEEL
red9-0.1.0.dist-info/entry_points.txt
red9-0.1.0.dist-info/licenses/LICENSE
red9-0.1.0.dist-info/RECORD
